py_scdb-0.2.2.dist-info/METADATA
py_scdb-0.2.2.dist-info/WHEEL
py_scdb-0.2.2.dist-info/license_files/LICENSE-APACHE
py_scdb-0.2.2.dist-info/license_files/LICENSE-MIT
py_scdb/py.typed.py
py_scdb/py_scdb.pyi
py_scdb/__init__.py
py_scdb/py_scdb.cp39-win_amd64.pyd
py_scdb-0.2.2.dist-info/RECORD
