Metadata-Version: 2.1
Name: py_scdb
Version: 0.2.2
Classifier: Programming Language :: Rust
Classifier: Programming Language :: Python :: Implementation :: CPython
Classifier: Programming Language :: Python :: Implementation :: PyPy
Requires-Dist: pytest>=7.2.0; extra == 'test'
Requires-Dist: pytest-benchmark>=4.0.0; extra == 'test'
Requires-Dist: pytest-lazy-fixture>=0.6.3; extra == 'test'
Requires-Dist: pytest-asyncio>=0.20.1; extra == 'test'
Provides-Extra: test
License-File: LICENSE-APACHE
License-File: LICENSE-MIT
Summary: A very simple and fast key-value store but persisting data to disk, with a 'localStorage-like' API for python.
Keywords: key-value-store,cache,disk-cache,database,localStorage
Author-email: Martin Ahindura  <team.sopherapps@gmail.com>
Requires-Python: >=3.7
Project-URL: documentation, https://github.com/sopherapps/py_scdb
Project-URL: homepage, https://github.com/sopherapps/py_scdb
Project-URL: repository, https://github.com/sopherapps/py_scdb
Project-URL: changelog, https://github.com/sopherapps/py_scdb/blob/master/CHANGELOG.md
